DyGyS/Directed_class.py
DyGyS/Undirected_class.py
DyGyS/__init__.py
DyGyS/ensemble_Functions.py
DyGyS/ll_Functions_conditional.py
DyGyS/ll_Functions_econometrics.py
DyGyS/ll_Functions_integrated.py
DyGyS/netstats_Functions.py
DyGyS/solver_Functions.py
DyGyS-0.0.5.dist-info/LICENSE
DyGyS-0.0.5.dist-info/METADATA
DyGyS-0.0.5.dist-info/WHEEL
DyGyS-0.0.5.dist-info/top_level.txt
DyGyS-0.0.5.dist-info/RECORD
