Metadata-Version: 2.1
Name: DyGyS
Version: 0.0.5
Summary: DyGyS is a package for Maximum Entropy regression models with gravity specification for undirected and directed network data. Moreover, it can solve them, generate the graph ensemble, compute several network statistics, calculate model selection measures such as AIC and BIC and quantify their reproduction accuracy in topological and weighted properties.
Author-email: Marzio Di Vece <marzio.divece@imtlucca.it>
Project-URL: Homepage, https://github.com/MarsMDK/DyGyS
Keywords: maximum entropy methods,econometrics,regression,graph,network
Classifier: License :: OSI Approved :: GNU General Public License v3 (GPLv3)
Classifier: Programming Language :: Python :: 3.8
Classifier: Programming Language :: Python :: 3.9
Requires-Python: >=3.8
License-File: LICENSE
Requires-Dist: numpy (>=1.21.5)
Requires-Dist: numba (>=0.55.1)
Requires-Dist: numba-scipy (>=0.3.1)
Requires-Dist: tomli ; python_version >= "3.8"
Provides-Extra: dev
Requires-Dist: pytest ; extra == 'dev'
